shiv/__init__.py
shiv/__main__.py
shiv/builder.py
shiv/cli.py
shiv/constants.py
shiv/info.py
shiv/pip.py
shiv/bootstrap/__init__.py
shiv/bootstrap/environment.py
shiv/bootstrap/filelock.py
shiv/bootstrap/interpreter.py
shiv_userdirs-1.0.3.dist-info/LICENSE
shiv_userdirs-1.0.3.dist-info/METADATA
shiv_userdirs-1.0.3.dist-info/WHEEL
shiv_userdirs-1.0.3.dist-info/entry_points.txt
shiv_userdirs-1.0.3.dist-info/top_level.txt
shiv_userdirs-1.0.3.dist-info/RECORD
