Metadata-Version: 2.1
Name: shiv-userdirs
Version: 1.0.3
Summary: Python SHIV-version, which creates user owned directires if SHIV_ROOT is used. SHIV is a command line utility for building fully self contained Python zipapps.
Home-page: https://github.com/manfred-kaiser/shiv
Author: Manfred Kaiser
Author-email: manfred.kaiser@ssh-mitm.at
License: BSD License
Classifier: License :: OSI Approved :: BSD License
Classifier: Programming Language :: Python :: 3 :: Only
Classifier: Programming Language :: Python :: 3
Classifier: Programming Language :: Python :: 3.6
Classifier: Programming Language :: Python :: 3.7
Classifier: Programming Language :: Python :: 3.8
Classifier: Programming Language :: Python :: 3.9
Classifier: Programming Language :: Python :: 3.10
Requires-Python: >=3.6
License-File: LICENSE
Requires-Dist: click (!=7.0,>=6.7)
Requires-Dist: pip (>=9.0.3)
Requires-Dist: setuptools
Requires-Dist: importlib-resources ; python_version < "3.7"
